pycaw/__init__.py
pycaw_rf-20210213.dist-info/LICENSE
pycaw_rf-20210213.dist-info/WHEEL
pycaw_rf-20210213.dist-info/METADATA
pycaw_rf-20210213.dist-info/RECORD
